thank_you_stars/__init__.py
thank_you_stars/__main__.py
thank_you_stars/__version__.py
thank_you_stars/_cache.py
thank_you_stars/_common.py
thank_you_stars/_config.py
thank_you_stars/_const.py
thank_you_stars/_extractor.py
thank_you_stars/_github.py
thank_you_stars/_logger.py
thank_you_stars/_pip_show.py
thank_you_stars/_printer.py
thank_you_stars/_starred.py
thank_you_stars-0.1.0.dist-info/LICENSE
thank_you_stars-0.1.0.dist-info/METADATA
thank_you_stars-0.1.0.dist-info/WHEEL
thank_you_stars-0.1.0.dist-info/entry_points.txt
thank_you_stars-0.1.0.dist-info/top_level.txt
thank_you_stars-0.1.0.dist-info/RECORD
