Metadata-Version: 2.1
Name: thank-you-stars
Version: 0.1.0
Summary: thank-you-stars is a CLI tool to stars to a PyPI package and its dependencies hosted on GitHub.
Home-page: https://github.com/thombashi/thank-you-stars
Author: Tsuyoshi Hombashi
Author-email: tsuyoshi.hombashi@gmail.com
License: MIT License
Project-URL: Source, https://github.com/thombashi/thank-you-stars
Project-URL: Tracker, https://github.com/thombashi/thank-you-stars/issues
Keywords: GitHub,Stars,PyPI packages
Platform: UNKNOWN
Classifier: Development Status :: 4 - Beta
Classifier: Environment :: Console
Classifier: Intended Audience :: Developers
Classifier: Intended Audience :: Information Technology
Classifier: License :: OSI Approved :: MIT License
Classifier: Operating System :: OS Independent
Classifier: Programming Language :: Python :: 3
Classifier: Programming Language :: Python :: 3.5
Classifier: Programming Language :: Python :: 3.6
Classifier: Programming Language :: Python :: 3.7
Classifier: Programming Language :: Python :: 3.8
Classifier: Topic :: Terminals
Classifier: Topic :: Utilities
Requires-Python: >=3.5
Requires-Dist: setuptools (>=38.3.0)
Requires-Dist: appconfigpy (<2,>=1.0.1)
Requires-Dist: colorama (<1,>=0.3.7)
Requires-Dist: DateTimeRange (<2,>=1.0.0)
Requires-Dist: Logbook (<2.0.0,>=0.12.3)
Requires-Dist: mbstrdecoder (<2,>=1.0.0)
Requires-Dist: msgfy (<1,>=0.0.6)
Requires-Dist: path.py (<13)
Requires-Dist: pathvalidate (<3)
Requires-Dist: PyGithub (<2,>=1.43.7)
Requires-Dist: pytablewriter (<1,>=0.51.0)
Requires-Dist: retryrequests (<1,>=0.0.2)
Requires-Dist: simplejson (<4,>=3.8.1)
Requires-Dist: subprocrunner (<2,>=1.2.1)
Requires-Dist: tqdm (<5,>=4.31.1)
Provides-Extra: test
Requires-Dist: pytest ; extra == 'test'
